[
  {
    "id": "track_fee_11_20",
    "name": "Track Fee (11-20)",
    "description": "Additional fee for songs with 11-20 tracks",
    "price": 75,
    "priceType": "flat",
    "category": "track_fee",
    "productType": "mixing",
    "minThreshold": 11,
    "maxThreshold": 20
  },
  {
    "id": "track_fee_21_30",
    "name": "Track Fee (21-30)",
    "description": "Additional fee for songs with 21-30 tracks",
    "price": 150,
    "priceType": "flat",
    "category": "track_fee",
    "productType": "mixing",
    "minThreshold": 21,
    "maxThreshold": 30
  },
  {
    "id": "track_fee_31_40",
    "name": "Track Fee (31-40)",
    "description": "Additional fee for songs with 31-40 tracks",
    "price": 225,
    "priceType": "flat",
    "category": "track_fee",
    "productType": "mixing",
    "minThreshold": 31,
    "maxThreshold": 40
  },
  {
    "id": "track_fee_41_50",
    "name": "Track Fee (41-50)",
    "description": "Additional fee for songs with 41-50 tracks",
    "price": 300,
    "priceType": "flat",
    "category": "track_fee",
    "productType": "mixing",
    "minThreshold": 41,
    "maxThreshold": 50
  },
  {
    "id": "track_fee_high_51_60",
    "name": "High Track Fee (51-60)",
    "description": "Additional fee for high track count songs with 51-60 tracks",
    "price": 100,
    "priceType": "flat",
    "category": "track_fee_high",
    "productType": "mixing",
    "minThreshold": 51,
    "maxThreshold": 60
  },
  {
    "id": "track_fee_high_61_70",
    "name": "High Track Fee (61-70)",
    "description": "Additional fee for high track count songs with 61-70 tracks",
    "price": 200,
    "priceType": "flat",
    "category": "track_fee_high",
    "productType": "mixing",
    "minThreshold": 61,
    "maxThreshold": 70
  },
  {
    "id": "track_fee_high_71_80",
    "name": "High Track Fee (71-80)",
    "description": "Additional fee for high track count songs with 71-80 tracks",
    "price": 300,
    "priceType": "flat",
    "category": "track_fee_high",
    "productType": "mixing",
    "minThreshold": 71,
    "maxThreshold": 80
  },
  {
    "id": "track_fee_high_81_90",
    "name": "High Track Fee (81-90)",
    "description": "Additional fee for high track count songs with 81-90 tracks",
    "price": 400,
    "priceType": "flat",
    "category": "track_fee_high",
    "productType": "mixing",
    "minThreshold": 81,
    "maxThreshold": 90
  },
  {
    "id": "track_fee_high_91_100",
    "name": "High Track Fee (91-100)",
    "description": "Additional fee for high track count songs with 91-100 tracks",
    "price": 500,
    "priceType": "flat",
    "category": "track_fee_high",
    "productType": "mixing",
    "minThreshold": 91,
    "maxThreshold": 100
  },
  {
    "id": "length_fee_5min",
    "name": "Extended Length Fee (5+ min)",
    "description": "Additional fee for songs over 5 minutes",
    "price": 50,
    "priceType": "flat",
    "category": "length_fee",
    "productType": "mixing",
    "minThreshold": 5,
    "maxThreshold": 10
  },
  {
    "id": "length_fee_10min",
    "name": "Extended Length Fee (10+ min)",
    "description": "Additional fee for songs over 10 minutes",
    "price": 100,
    "priceType": "flat",
    "category": "length_fee",
    "productType": "mixing",
    "minThreshold": 10,
    "maxThreshold": 15
  },
  {
    "id": "length_fee_15min",
    "name": "Extended Length Fee (15+ min)",
    "description": "Additional fee for songs over 15 minutes",
    "price": 200,
    "priceType": "flat",
    "category": "length_fee",
    "productType": "mixing",
    "minThreshold": 15,
    "maxThreshold": null
  },
  {
    "id": "vocal_production",
    "name": "Vocal Production Mixing/Editing",
    "description": "Professional vocal production, mixing, and editing services",
    "price": 100,
    "priceType": "flat",
    "category": "addon",
    "productType": "mixing",
    "minThreshold": null,
    "maxThreshold": null
  },
  {
    "id": "drum_replacement",
    "name": "Drum Replacement/Production",
    "description": "Drum replacement and production services",
    "price": 150,
    "priceType": "flat",
    "category": "addon",
    "productType": "mixing",
    "minThreshold": null,
    "maxThreshold": null
  },
  {
    "id": "guitar_reamp",
    "name": "Guitar Re-Amplification/Production",
    "description": "Guitar re-amplification and production services",
    "price": 50,
    "priceType": "flat",
    "category": "addon",
    "productType": "mixing",
    "minThreshold": null,
    "maxThreshold": null
  },
  {
    "id": "virtual_session",
    "name": "Virtual In-Person Session",
    "description": "Virtual in-person mixing session ($100/hour, 4 hour minimum)",
    "price": 100,
    "priceType": "per_hour",
    "category": "addon",
    "productType": "mixing",
    "minThreshold": 4,
    "maxThreshold": null
  },
  {
    "id": "high_res_mixdown",
    "name": "High Resolution Mixdown",
    "description": "High resolution audio mixdown delivery",
    "price": 25,
    "priceType": "flat",
    "category": "delivery",
    "productType": "mixing",
    "minThreshold": null,
    "maxThreshold": null
  },
  {
    "id": "film_mixdown",
    "name": "Film Mixdown",
    "description": "Film-ready audio mixdown delivery",
    "price": 20,
    "priceType": "flat",
    "category": "delivery",
    "productType": "mixing",
    "minThreshold": null,
    "maxThreshold": null
  },
  {
    "id": "mixed_stems",
    "name": "Mixed Stems",
    "description": "Individual stem exports ($20 base + $5 per 10 tracks)",
    "price": 20,
    "priceType": "per_ten_tracks",
    "category": "delivery",
    "productType": "mixing",
    "minThreshold": null,
    "maxThreshold": null
  },
  {
    "id": "extended_archival",
    "name": "Extended Archival",
    "description": "Extended project archival storage",
    "price": 25,
    "priceType": "flat",
    "category": "delivery",
    "productType": "mixing",
    "minThreshold": null,
    "maxThreshold": null
  },
  {
    "id": "rush_delivery",
    "name": "Rush Delivery",
    "description": "Expedited delivery (doubles song base cost)",
    "price": 2,
    "priceType": "multiplier",
    "category": "delivery",
    "productType": "mixing",
    "minThreshold": null,
    "maxThreshold": null
  },
  {
    "id": "vinyl_master",
    "name": "Vinyl Mastering",
    "description": "Optimized mastering for vinyl pressing",
    "price": 50,
    "priceType": "flat",
    "category": "addon",
    "productType": "mastering",
    "minThreshold": null,
    "maxThreshold": null
  },
  {
    "id": "streaming_master",
    "name": "Streaming Mastering",
    "description": "Optimized for Spotify, Tidal, and other streaming platforms",
    "price": 25,
    "priceType": "flat",
    "category": "addon",
    "productType": "mastering",
    "minThreshold": null,
    "maxThreshold": null
  },
  {
    "id": "redbook_master",
    "name": "Redbook CD Mastering",
    "description": "CD-quality mastering to Redbook specifications",
    "price": 25,
    "priceType": "flat",
    "category": "addon",
    "productType": "mastering",
    "minThreshold": null,
    "maxThreshold": null
  },
  {
    "id": "stem_master_2_8",
    "name": "Stem Mastering (2-8 Stems)",
    "description": "Stereo mastering from 2-8 stems",
    "price": 50,
    "priceType": "flat",
    "category": "addon",
    "productType": "mastering",
    "minThreshold": 2,
    "maxThreshold": 8
  },
  {
    "id": "stem_master_9_16",
    "name": "Stem Mastering (9-16 Stems)",
    "description": "Stereo mastering from 9-16 stems",
    "price": 100,
    "priceType": "flat",
    "category": "addon",
    "productType": "mastering",
    "minThreshold": 9,
    "maxThreshold": 16
  },
  {
    "id": "stem_master_17_24",
    "name": "Stem Mastering (17-24 Stems)",
    "description": "Stereo mastering from 17-24 stems",
    "price": 150,
    "priceType": "flat",
    "category": "addon",
    "productType": "mastering",
    "minThreshold": 17,
    "maxThreshold": 24
  },
  {
    "id": "stem_master_25_32",
    "name": "Stem Mastering (25-32 Stems)",
    "description": "Stereo mastering from 25-32 stems",
    "price": 200,
    "priceType": "flat",
    "category": "addon",
    "productType": "mastering",
    "minThreshold": 25,
    "maxThreshold": 32
  },
  {
    "id": "restoration_remaster",
    "name": "Restoration Remastering",
    "description": "Audio restoration and remastering for archival or legacy recordings",
    "price": 350,
    "priceType": "flat",
    "category": "addon",
    "productType": "mastering",
    "minThreshold": null,
    "maxThreshold": null
  },
  {
    "id": "virtual_session",
    "name": "Virtual In-Person Session",
    "description": "Live virtual session with engineer ($100/hour, 4 hour minimum)",
    "price": 100,
    "priceType": "per_hour",
    "category": "addon",
    "productType": "mastering",
    "minThreshold": 4,
    "maxThreshold": null
  },
  {
    "id": "high_res_master",
    "name": "High Resolution Master",
    "description": "96kHz/24-bit high resolution master files",
    "price": 25,
    "priceType": "flat",
    "category": "delivery",
    "productType": "mastering",
    "minThreshold": null,
    "maxThreshold": null
  },
  {
    "id": "ddp_image",
    "name": "DDP Image",
    "description": "DDP image for CD replication",
    "price": 25,
    "priceType": "flat",
    "category": "delivery",
    "productType": "mastering",
    "minThreshold": null,
    "maxThreshold": null
  },
  {
    "id": "isrc_encoding",
    "name": "ISRC Encoding",
    "description": "ISRC code embedding for distribution",
    "price": 10,
    "priceType": "flat",
    "category": "delivery",
    "productType": "mastering",
    "minThreshold": null,
    "maxThreshold": null
  },
  {
    "id": "rush_master",
    "name": "Rush Delivery",
    "description": "Expedited delivery (doubles song price)",
    "price": 2,
    "priceType": "multiplier",
    "category": "delivery",
    "productType": "mastering",
    "minThreshold": null,
    "maxThreshold": null
  },
  {
    "id": "mix_revision",
    "name": "Project Mix Revision",
    "description": "Request mix changes to any/all songs in a project",
    "price": 250,
    "priceType": "flat",
    "category": "addon",
    "productType": "mixing",
    "minThreshold": null,
    "maxThreshold": 10
  },
  {
    "id": "mastering_revision",
    "name": "Project Mastering Revision",
    "description": "Request mastering changes to any/all songs in a project",
    "price": 125,
    "priceType": "flat",
    "category": "addon",
    "productType": "mastering",
    "minThreshold": null,
    "maxThreshold": null
  }
]
